notion_dev/__init__.py
notion_dev/cli/main.py
notion_dev/core/asana_client.py
notion_dev/core/config.py
notion_dev/core/context_builder.py
notion_dev/core/github_client.py
notion_dev/core/models.py
notion_dev/core/notion_client.py
notion_dev/mcp_server/__init__.py
notion_dev/mcp_server/auth.py
notion_dev/mcp_server/code_tools.py
notion_dev/mcp_server/config.py
notion_dev/mcp_server/oauth_server.py
notion_dev/mcp_server/remote_backend.py
notion_dev/mcp_server/server.py
notion_dev-2.0.12.dist-info/licenses/LICENSE
notion_dev-2.0.12.dist-info/METADATA
notion_dev-2.0.12.dist-info/WHEEL
notion_dev-2.0.12.dist-info/entry_points.txt
notion_dev-2.0.12.dist-info/top_level.txt
notion_dev-2.0.12.dist-info/RECORD
