Metadata-Version: 2.4
Name: notion-dev
Version: 2.0.12
Summary: Integration tool for Notion, Asana and Git workflows with MCP server support
Home-page: https://github.com/yourusername/notion-dev
Author: Your Name
Author-email: Your Name <your.email@example.com>
License: MIT
Project-URL: Homepage, https://github.com/yourusername/notion-dev
Project-URL: Documentation, https://notion-dev.readthedocs.io
Project-URL: Repository, https://github.com/yourusername/notion-dev
Project-URL: Issues, https://github.com/yourusername/notion-dev/issues
Classifier: Development Status :: 4 - Beta
Classifier: Intended Audience :: Developers
Classifier: License :: OSI Approved :: MIT License
Classifier: Programming Language :: Python :: 3
Classifier: Programming Language :: Python :: 3.10
Classifier: Programming Language :: Python :: 3.11
Classifier: Programming Language :: Python :: 3.12
Classifier: Programming Language :: Python :: 3.13
Classifier: Topic :: Software Development :: Libraries :: Python Modules
Classifier: Topic :: Office/Business :: Scheduling
Requires-Python: >=3.10
License-File: LICENSE
Requires-Dist: asana>=3.2.0
Requires-Dist: notion-client>=2.2.1
Requires-Dist: click>=8.1.7
Requires-Dist: pyyaml>=6.0.1
Requires-Dist: rich>=13.7.0
Requires-Dist: requests>=2.31.0
Requires-Dist: gitpython>=3.1.40
Requires-Dist: urllib3<2
Provides-Extra: mcp
Requires-Dist: mcp>=1.0.0; extra == "mcp"
Provides-Extra: dev
Requires-Dist: pytest>=7.4.0; extra == "dev"
Requires-Dist: pytest-cov>=4.1.0; extra == "dev"
Requires-Dist: pytest-mock>=3.11.1; extra == "dev"
Requires-Dist: pytest-asyncio>=0.21.0; extra == "dev"
Requires-Dist: black>=23.7.0; extra == "dev"
Requires-Dist: flake8>=6.1.0; extra == "dev"
Requires-Dist: mypy>=1.5.0; extra == "dev"
Requires-Dist: pre-commit>=3.3.3; extra == "dev"
Dynamic: author
Dynamic: home-page
Dynamic: license-file
Dynamic: requires-python
